factory_generator/__init__.py
factory_generator/__version__.py
factory_generator/apps.py
factory_generator/encoders.py
factory_generator/generators.py
factory_generator/utils.py
factory_generator/management/__init__.py
factory_generator/management/base.py
factory_generator/management/commands/__init__.py
factory_generator/management/commands/generate_to_db.py
factory_generator/management/commands/generate_to_json.py
django_factory_boy_generator-1.0.4.dist-info/LICENSE
django_factory_boy_generator-1.0.4.dist-info/METADATA
django_factory_boy_generator-1.0.4.dist-info/WHEEL
django_factory_boy_generator-1.0.4.dist-info/top_level.txt
django_factory_boy_generator-1.0.4.dist-info/RECORD
