Metadata-Version: 2.1
Name: django-factory-boy-generator
Version: 1.0.4
Summary: This package provides django app to generate data for django apps using factories.
Home-page: https://github.com/V-ampire/django-factory-generator
Author: V-ampire
Author-email: webjob010@gmail.com
License: MIT
Keywords: django,factory,generator,generate_db,generate_model_dict,generate_model_json,factory-boy
Platform: UNKNOWN
Classifier: License :: OSI Approved :: MIT License
Classifier: Programming Language :: Python
Classifier: Programming Language :: Python :: 3
Classifier: Programming Language :: Python :: 3.6
Classifier: Programming Language :: Python :: 3.7
Classifier: Programming Language :: Python :: 3.8
Classifier: Programming Language :: Python :: Implementation :: CPython
Requires-Python: >=3.6.0
License-File: LICENSE
Requires-Dist: factory-boy
Provides-Extra: dev
Requires-Dist: django ; extra == 'dev'
Requires-Dist: pytest-django ; extra == 'dev'
Requires-Dist: pytest-pythonpath ; extra == 'dev'
Requires-Dist: tox ; extra == 'dev'
